README.rst
setup.py
turbotools/__init__.py
turbotools/utils.py
turbotools.egg-info/PKG-INFO
turbotools.egg-info/SOURCES.txt
turbotools.egg-info/dependency_links.txt
turbotools.egg-info/top_level.txt