Metadata-Version: 1.1
Name: turbotools
Version: 0.0.2
Summary: Toolset. 
Home-page: https://github.com/anshengme/turbotools
Author: ansheng
Author-email: ianshengme@gmail.com
License: LICENSE.txt
Platform: UNKNOWN
Classifier: Programming Language :: Python :: 3.6
